sparksteps/__init__.py
sparksteps/__main__.py
sparksteps/cluster.py
sparksteps/poll.py
sparksteps/pricing.py
sparksteps/steps.py
sparksteps-3.0.1.dist-info/LICENSE
sparksteps-3.0.1.dist-info/METADATA
sparksteps-3.0.1.dist-info/WHEEL
sparksteps-3.0.1.dist-info/entry_points.txt
sparksteps-3.0.1.dist-info/top_level.txt
sparksteps-3.0.1.dist-info/RECORD
