Metadata-Version: 2.1
Name: sparksteps
Version: 3.0.1
Summary: Workflow tool to launch Spark jobs on AWS EMR
Home-page: https://github.com/jwplayer/sparksteps
Author: Kamil Sindi
Author-email: kamil@jwplayer.com
License: Apache License 2.0
Keywords: aws,emr,pyspark,spark,boto
Platform: UNKNOWN
Classifier: Development Status :: 4 - Beta
Classifier: Intended Audience :: Developers
Classifier: License :: OSI Approved :: Apache Software License
Classifier: Environment :: Console
Classifier: Programming Language :: Python :: 3.6
Classifier: Programming Language :: Python :: 3.7
Classifier: Programming Language :: Python :: 3.8
Requires-Python: >=3.6
Requires-Dist: boto3 (>=1.3.1)
Requires-Dist: polling (==0.3.0)
